odeo/__init__.py
odeo/api_signature.py
odeo/client.py
odeo/exceptions.py
odeo/models/__init__.py
odeo/models/cash.py
odeo/models/disbursement.py
odeo/models/payment_gateway.py
odeo/models/sub_user.py
odeo/services/__init__.py
odeo/services/base.py
odeo/services/cash.py
odeo/services/disbursement.py
odeo/services/payment_gateway.py
odeo/services/sub_user.py
odeo_python_sdk-1.0.0.dist-info/LICENSE
odeo_python_sdk-1.0.0.dist-info/WHEEL
odeo_python_sdk-1.0.0.dist-info/METADATA
odeo_python_sdk-1.0.0.dist-info/RECORD
